DDaCA/Turing-Machine/modules/d_latch.v
module d_latch (
    input d, e,
    output q
);
    wire d_n, and1, and2, q_n;

    not d_inv(d_n, d);
    and and_upper(and1, d_n, e);
    and and_lower(and2, d, e);
    nor nor_upper(q, and1, q_n);
    nor nor_lower(q_n, and2, q);
endmodule

DDaCA/KALI/modules/d_flip_flop.v
`include "d_latch.v"

module d_flip_flop (
    input d, clk,
    output q
);
    wire clk_n, q_tmp;

    not clk_inv(clk_n, clk);
    d_latch master(d, clk_n, q_tmp);
    d_latch slave(q_tmp, clk, q);
endmodule

DDaCA/KALI/test_bench/modules/d_flip_flop_tb.v
module d_flip_flop_tb ();
    reg clk = 0, d;
    wire q;

    always #5 clk = !clk;

    d_flip_flop dut(d, clk, q);

    initial begin
        $dumpfile("d_flip_flop.vcd");
        $dumpvars(0, d_flip_flop_tb);

        d = 0;
        #10;
        d = 1;
        #3;
        d = 0;
        #1;
        d = 1;
        #4;
        d = 0;
        #8;
        d = 1;
        #6;
        d = 0;
        #7;
        d = 1;
        #7;
        d = 0;
        #20;
        $finish;
    end

    initial
     $monitor("At time %t, q = %h",
              $time, q);
endmodule

DDaCA/KALI/test_bench/modules/d_flip_flop.vcd
$date
	Sun Jul  4 14:05:21 2021
$end
$version
	Icarus Verilog
$end
$timescale
	1s
$end
$scope module d_flip_flop_tb $end
$var wire 1 ! q $end
$var reg 1 " clk $end
$var reg 1 # d $end
$scope module dut $end
$var wire 1 " clk $end
$var wire 1 $ clk_n $end
$var wire 1 # d $end
$var wire 1 % q_tmp $end
$var wire 1 ! q $end
$scope module master $end
$var wire 1 & and1 $end
$var wire 1 ' and2 $end
$var wire 1 # d $end
$var wire 1 ( d_n $end
$var wire 1 $ e $end
$var wire 1 % q $end
$var wire 1 ) q_n $end
$upscope $end
$scope module slave $end
$var wire 1 * and1 $end
$var wire 1 + and2 $end
$var wire 1 % d $end
$var wire 1 , d_n $end
$var wire 1 " e $end
$var wire 1 ! q $end
$var wire 1 - q_n $end
$upscope $end
$upscope $end
$upscope $end
$enddefinitions $end
#0
$dumpvars
x-
1,
0+
0*
1)
1(
0'
1&
0%
1$
0#
0"
x!
$end
#5
1-
0&
0!
0$
1*
1"
#10
0,
1%
0)
1'
1$
0*
0(
0"
1#
#13
1)
1,
0%
1&
1(
0'
0#
#14
0,
1%
0&
0)
0(
1'
1#
#15
1!
0'
0-
0$
1+
1"
#18
1(
0#
#20
1)
1,
0%
1&
1$
0+
0"
#25
1-
0&
0!
0$
1*
1"
#26
0(
1#
#30
0,
1%
0)
1'
1$
0*
0"
#32
1)
1,
0%
1&
1(
0'
0#
#35
0&
0$
1*
1"
#39
0(
1#
#40
0,
1%
0)
1'
1$
0*
0"
#45
1!
0'
0-
0$
1+
1"
#46
1(
0#
#50
1)
1,
0%
1&
1$
0+
0"
#55
1-
0&
0!
0$
1*
1"
#60
1&
1$
0*
0"
#65
0&
0$
1*
1"
