DDaCA/Turing-Machine/modules/d_latch.v
module d_latch (
    input d, e,
    output q
);
    wire d_n, and1, and2, q_n;

    not d_inv(d_n, d);
    and and_upper(and1, d_n, e);
    and and_lower(and2, d, e);
    nor nor_upper(q, and1, q_n);
    nor nor_lower(q_n, and2, q);
endmodule

DDaCA/KALI/test_bench/modules/d_latch_tb.v
module d_latch_tb ();
    reg en, d;
    wire q;

    d_latch dut(d, en, q);

    initial begin
        $dumpfile("d_latch.vcd");
        $dumpvars(0, d_latch_tb);

        en = 0; d = 0;  #10; // q = x
        d = 1;          #10; // q = x
        en = 1; d = 0;  #10; // q = 0
        d = 1;          #10; // q = 1
        en = 0; d = 0;  #10; // q = 1
        d = 1;          #10; // q = 1
        d = 0;          #10; // q = 1
        en = 1;         #10; // q = 0
        d = 1;          #10; // q = 1
        en = 0;         #10; // q = 1
        d = 0;          #10; // q = 1
        $finish;
    end

    initial
     $monitor("At time %t, value = %h (%0d)",
              $time, q, q);
endmodule

DDaCA/KALI/test_bench/modules/d_latch.vcd
$date
	Sun Jul  4 14:00:55 2021
$end
$version
	Icarus Verilog
$end
$timescale
	1s
$end
$scope module d_latch_tb $end
$var wire 1 ! q $end
$var reg 1 " d $end
$var reg 1 # en $end
$scope module dut $end
$var wire 1 $ and1 $end
$var wire 1 % and2 $end
$var wire 1 " d $end
$var wire 1 & d_n $end
$var wire 1 # e $end
$var wire 1 ! q $end
$var wire 1 ' q_n $end
$upscope $end
$upscope $end
$enddefinitions $end
#0
$dumpvars
x'
1&
0%
0$
0#
0"
x!
$end
#10
0&
1"
#20
1'
0!
1$
1&
0"
1#
#30
1!
0$
0'
0&
1%
1"
#40
1&
0%
0"
0#
#50
0&
1"
#60
1&
0"
#70
1'
0!
1$
1#
#80
1!
0$
0'
0&
1%
1"
#90
0%
0#
#100
1&
0"
