DDaCA/Turing-Machine/modules/d_latch.v
module d_latch (
    input d, e,
    output q
);
    wire d_n, and1, and2, q_n;

    not d_inv(d_n, d);
    and and_upper(and1, d_n, e);
    and and_lower(and2, d, e);
    nor nor_upper(q, and1, q_n);
    nor nor_lower(q_n, and2, q);
endmodule

DDaCA/KALI/modules/d_flip_flop.v
`include "d_latch.v"

module d_flip_flop (
    input d, clk,
    output q
);
    wire clk_n, q_tmp;

    not clk_inv(clk_n, clk);
    d_latch master(d, clk_n, q_tmp);
    d_latch slave(q_tmp, clk, q);
endmodule

DDaCA/Turing-Machine/modules/register.v
`include "d_flip_flop.v"

module register #(
    parameter DATA_WIDTH = 16
) (
    input [DATA_WIDTH-1:0] d,
    input e,
    output [DATA_WIDTH-1:0] q
);
    generate
        genvar i;

        for (i = 0; i < DATA_WIDTH; i = i + 1) begin
            d_flip_flop dff(d[i], e, q[i]);
        end
    endgenerate
endmodule

DDaCA/KALI/test_bench/modules/register_tb.v
module register_tb ();
    parameter DATA_WIDTH = 16;

    reg clk = 0;
    reg [DATA_WIDTH-1:0] d;
    wire [DATA_WIDTH-1:0] q;

    always #5 clk = !clk;

    register dut(d, clk, q);

    initial begin
        $dumpfile("register.vcd");
        $dumpvars(0, register_tb);

        d = 16'b11;
        #10;
        d = 16'b1001;
        #3;
        d = 16'b1000_0000_0011_0001;
        #1;
        d = 16'b110;
        #4;
        d = 16'b11;
        #8;
        d = 16'b1000;
        #6;
        d = 16'hFF_FF;
        #7;
        d = 16'b0;
        #7;
        d = 16'b11;
        #20;
        $finish;
    end

    initial
     $monitor("At time %t, q = %h",
              $time, q);
endmodule

DDaCA/KALI/test_bench/modules/register.vcd
$date
	Sun Jul  4 14:46:48 2021
$end
$version
	Icarus Verilog
$end
$timescale
	1s
$end
$scope module register_tb $end
$var wire 16 ! q [15:0] $end
$var reg 1 " clk $end
$var reg 16 # d [15:0] $end
$scope module dut $end
$var wire 16 $ d [15:0] $end
$var wire 1 " e $end
$var wire 16 % q [15:0] $end
$scope begin genblk1[0] $end
$scope module dff $end
$var wire 1 " clk $end
$var wire 1 & clk_n $end
$var wire 1 ' d $end
$var wire 1 ( q_tmp $end
$var wire 1 ) q $end
$scope module master $end
$var wire 1 * and1 $end
$var wire 1 + and2 $end
$var wire 1 ' d $end
$var wire 1 , d_n $end
$var wire 1 & e $end
$var wire 1 ( q $end
$var wire 1 - q_n $end
$upscope $end
$scope module slave $end
$var wire 1 . and1 $end
$var wire 1 / and2 $end
$var wire 1 ( d $end
$var wire 1 0 d_n $end
$var wire 1 " e $end
$var wire 1 ) q $end
$var wire 1 1 q_n $end
$upscope $end
$upscope $end
$upscope $end
$scope begin genblk1[1] $end
$scope module dff $end
$var wire 1 " clk $end
$var wire 1 2 clk_n $end
$var wire 1 3 d $end
$var wire 1 4 q_tmp $end
$var wire 1 5 q $end
$scope module master $end
$var wire 1 6 and1 $end
$var wire 1 7 and2 $end
$var wire 1 3 d $end
$var wire 1 8 d_n $end
$var wire 1 2 e $end
$var wire 1 4 q $end
$var wire 1 9 q_n $end
$upscope $end
$scope module slave $end
$var wire 1 : and1 $end
$var wire 1 ; and2 $end
$var wire 1 4 d $end
$var wire 1 < d_n $end
$var wire 1 " e $end
$var wire 1 5 q $end
$var wire 1 = q_n $end
$upscope $end
$upscope $end
$upscope $end
$scope begin genblk1[2] $end
$scope module dff $end
$var wire 1 " clk $end
$var wire 1 > clk_n $end
$var wire 1 ? d $end
$var wire 1 @ q_tmp $end
$var wire 1 A q $end
$scope module master $end
$var wire 1 B and1 $end
$var wire 1 C and2 $end
$var wire 1 ? d $end
$var wire 1 D d_n $end
$var wire 1 > e $end
$var wire 1 @ q $end
$var wire 1 E q_n $end
$upscope $end
$scope module slave $end
$var wire 1 F and1 $end
$var wire 1 G and2 $end
$var wire 1 @ d $end
$var wire 1 H d_n $end
$var wire 1 " e $end
$var wire 1 A q $end
$var wire 1 I q_n $end
$upscope $end
$upscope $end
$upscope $end
$scope begin genblk1[3] $end
$scope module dff $end
$var wire 1 " clk $end
$var wire 1 J clk_n $end
$var wire 1 K d $end
$var wire 1 L q_tmp $end
$var wire 1 M q $end
$scope module master $end
$var wire 1 N and1 $end
$var wire 1 O and2 $end
$var wire 1 K d $end
$var wire 1 P d_n $end
$var wire 1 J e $end
$var wire 1 L q $end
$var wire 1 Q q_n $end
$upscope $end
$scope module slave $end
$var wire 1 R and1 $end
$var wire 1 S and2 $end
$var wire 1 L d $end
$var wire 1 T d_n $end
$var wire 1 " e $end
$var wire 1 M q $end
$var wire 1 U q_n $end
$upscope $end
$upscope $end
$upscope $end
$scope begin genblk1[4] $end
$scope module dff $end
$var wire 1 " clk $end
$var wire 1 V clk_n $end
$var wire 1 W d $end
$var wire 1 X q_tmp $end
$var wire 1 Y q $end
$scope module master $end
$var wire 1 Z and1 $end
$var wire 1 [ and2 $end
$var wire 1 W d $end
$var wire 1 \ d_n $end
$var wire 1 V e $end
$var wire 1 X q $end
$var wire 1 ] q_n $end
$upscope $end
$scope module slave $end
$var wire 1 ^ and1 $end
$var wire 1 _ and2 $end
$var wire 1 X d $end
$var wire 1 ` d_n $end
$var wire 1 " e $end
$var wire 1 Y q $end
$var wire 1 a q_n $end
$upscope $end
$upscope $end
$upscope $end
$scope begin genblk1[5] $end
$scope module dff $end
$var wire 1 " clk $end
$var wire 1 b clk_n $end
$var wire 1 c d $end
$var wire 1 d q_tmp $end
$var wire 1 e q $end
$scope module master $end
$var wire 1 f and1 $end
$var wire 1 g and2 $end
$var wire 1 c d $end
$var wire 1 h d_n $end
$var wire 1 b e $end
$var wire 1 d q $end
$var wire 1 i q_n $end
$upscope $end
$scope module slave $end
$var wire 1 j and1 $end
$var wire 1 k and2 $end
$var wire 1 d d $end
$var wire 1 l d_n $end
$var wire 1 " e $end
$var wire 1 e q $end
$var wire 1 m q_n $end
$upscope $end
$upscope $end
$upscope $end
$scope begin genblk1[6] $end
$scope module dff $end
$var wire 1 " clk $end
$var wire 1 n clk_n $end
$var wire 1 o d $end
$var wire 1 p q_tmp $end
$var wire 1 q q $end
$scope module master $end
$var wire 1 r and1 $end
$var wire 1 s and2 $end
$var wire 1 o d $end
$var wire 1 t d_n $end
$var wire 1 n e $end
$var wire 1 p q $end
$var wire 1 u q_n $end
$upscope $end
$scope module slave $end
$var wire 1 v and1 $end
$var wire 1 w and2 $end
$var wire 1 p d $end
$var wire 1 x d_n $end
$var wire 1 " e $end
$var wire 1 q q $end
$var wire 1 y q_n $end
$upscope $end
$upscope $end
$upscope $end
$scope begin genblk1[7] $end
$scope module dff $end
$var wire 1 " clk $end
$var wire 1 z clk_n $end
$var wire 1 { d $end
$var wire 1 | q_tmp $end
$var wire 1 } q $end
$scope module master $end
$var wire 1 ~ and1 $end
$var wire 1 !" and2 $end
$var wire 1 { d $end
$var wire 1 "" d_n $end
$var wire 1 z e $end
$var wire 1 | q $end
$var wire 1 #" q_n $end
$upscope $end
$scope module slave $end
$var wire 1 $" and1 $end
$var wire 1 %" and2 $end
$var wire 1 | d $end
$var wire 1 &" d_n $end
$var wire 1 " e $end
$var wire 1 } q $end
$var wire 1 '" q_n $end
$upscope $end
$upscope $end
$upscope $end
$scope begin genblk1[8] $end
$scope module dff $end
$var wire 1 " clk $end
$var wire 1 (" clk_n $end
$var wire 1 )" d $end
$var wire 1 *" q_tmp $end
$var wire 1 +" q $end
$scope module master $end
$var wire 1 ," and1 $end
$var wire 1 -" and2 $end
$var wire 1 )" d $end
$var wire 1 ." d_n $end
$var wire 1 (" e $end
$var wire 1 *" q $end
$var wire 1 /" q_n $end
$upscope $end
$scope module slave $end
$var wire 1 0" and1 $end
$var wire 1 1" and2 $end
$var wire 1 *" d $end
$var wire 1 2" d_n $end
$var wire 1 " e $end
$var wire 1 +" q $end
$var wire 1 3" q_n $end
$upscope $end
$upscope $end
$upscope $end
$scope begin genblk1[9] $end
$scope module dff $end
$var wire 1 " clk $end
$var wire 1 4" clk_n $end
$var wire 1 5" d $end
$var wire 1 6" q_tmp $end
$var wire 1 7" q $end
$scope module master $end
$var wire 1 8" and1 $end
$var wire 1 9" and2 $end
$var wire 1 5" d $end
$var wire 1 :" d_n $end
$var wire 1 4" e $end
$var wire 1 6" q $end
$var wire 1 ;" q_n $end
$upscope $end
$scope module slave $end
$var wire 1 <" and1 $end
$var wire 1 =" and2 $end
$var wire 1 6" d $end
$var wire 1 >" d_n $end
$var wire 1 " e $end
$var wire 1 7" q $end
$var wire 1 ?" q_n $end
$upscope $end
$upscope $end
$upscope $end
$scope begin genblk1[10] $end
$scope module dff $end
$var wire 1 " clk $end
$var wire 1 @" clk_n $end
$var wire 1 A" d $end
$var wire 1 B" q_tmp $end
$var wire 1 C" q $end
$scope module master $end
$var wire 1 D" and1 $end
$var wire 1 E" and2 $end
$var wire 1 A" d $end
$var wire 1 F" d_n $end
$var wire 1 @" e $end
$var wire 1 B" q $end
$var wire 1 G" q_n $end
$upscope $end
$scope module slave $end
$var wire 1 H" and1 $end
$var wire 1 I" and2 $end
$var wire 1 B" d $end
$var wire 1 J" d_n $end
$var wire 1 " e $end
$var wire 1 C" q $end
$var wire 1 K" q_n $end
$upscope $end
$upscope $end
$upscope $end
$scope begin genblk1[11] $end
$scope module dff $end
$var wire 1 " clk $end
$var wire 1 L" clk_n $end
$var wire 1 M" d $end
$var wire 1 N" q_tmp $end
$var wire 1 O" q $end
$scope module master $end
$var wire 1 P" and1 $end
$var wire 1 Q" and2 $end
$var wire 1 M" d $end
$var wire 1 R" d_n $end
$var wire 1 L" e $end
$var wire 1 N" q $end
$var wire 1 S" q_n $end
$upscope $end
$scope module slave $end
$var wire 1 T" and1 $end
$var wire 1 U" and2 $end
$var wire 1 N" d $end
$var wire 1 V" d_n $end
$var wire 1 " e $end
$var wire 1 O" q $end
$var wire 1 W" q_n $end
$upscope $end
$upscope $end
$upscope $end
$scope begin genblk1[12] $end
$scope module dff $end
$var wire 1 " clk $end
$var wire 1 X" clk_n $end
$var wire 1 Y" d $end
$var wire 1 Z" q_tmp $end
$var wire 1 [" q $end
$scope module master $end
$var wire 1 \" and1 $end
$var wire 1 ]" and2 $end
$var wire 1 Y" d $end
$var wire 1 ^" d_n $end
$var wire 1 X" e $end
$var wire 1 Z" q $end
$var wire 1 _" q_n $end
$upscope $end
$scope module slave $end
$var wire 1 `" and1 $end
$var wire 1 a" and2 $end
$var wire 1 Z" d $end
$var wire 1 b" d_n $end
$var wire 1 " e $end
$var wire 1 [" q $end
$var wire 1 c" q_n $end
$upscope $end
$upscope $end
$upscope $end
$scope begin genblk1[13] $end
$scope module dff $end
$var wire 1 " clk $end
$var wire 1 d" clk_n $end
$var wire 1 e" d $end
$var wire 1 f" q_tmp $end
$var wire 1 g" q $end
$scope module master $end
$var wire 1 h" and1 $end
$var wire 1 i" and2 $end
$var wire 1 e" d $end
$var wire 1 j" d_n $end
$var wire 1 d" e $end
$var wire 1 f" q $end
$var wire 1 k" q_n $end
$upscope $end
$scope module slave $end
$var wire 1 l" and1 $end
$var wire 1 m" and2 $end
$var wire 1 f" d $end
$var wire 1 n" d_n $end
$var wire 1 " e $end
$var wire 1 g" q $end
$var wire 1 o" q_n $end
$upscope $end
$upscope $end
$upscope $end
$scope begin genblk1[14] $end
$scope module dff $end
$var wire 1 " clk $end
$var wire 1 p" clk_n $end
$var wire 1 q" d $end
$var wire 1 r" q_tmp $end
$var wire 1 s" q $end
$scope module master $end
$var wire 1 t" and1 $end
$var wire 1 u" and2 $end
$var wire 1 q" d $end
$var wire 1 v" d_n $end
$var wire 1 p" e $end
$var wire 1 r" q $end
$var wire 1 w" q_n $end
$upscope $end
$scope module slave $end
$var wire 1 x" and1 $end
$var wire 1 y" and2 $end
$var wire 1 r" d $end
$var wire 1 z" d_n $end
$var wire 1 " e $end
$var wire 1 s" q $end
$var wire 1 {" q_n $end
$upscope $end
$upscope $end
$upscope $end
$scope begin genblk1[15] $end
$scope module dff $end
$var wire 1 " clk $end
$var wire 1 |" clk_n $end
$var wire 1 }" d $end
$var wire 1 ~" q_tmp $end
$var wire 1 !# q $end
$scope module master $end
$var wire 1 "# and1 $end
$var wire 1 ## and2 $end
$var wire 1 }" d $end
$var wire 1 $# d_n $end
$var wire 1 |" e $end
$var wire 1 ~" q $end
$var wire 1 %# q_n $end
$upscope $end
$scope module slave $end
$var wire 1 &# and1 $end
$var wire 1 '# and2 $end
$var wire 1 ~" d $end
$var wire 1 (# d_n $end
$var wire 1 " e $end
$var wire 1 !# q $end
$var wire 1 )# q_n $end
$upscope $end
$upscope $end
$upscope $end
$upscope $end
$upscope $end
$enddefinitions $end
#0
$dumpvars
x)#
1(#
0'#
0&#
1%#
1$#
0##
1"#
x!#
0~"
0}"
1|"
x{"
1z"
0y"
0x"
1w"
1v"
0u"
1t"
xs"
0r"
0q"
1p"
xo"
1n"
0m"
0l"
1k"
1j"
0i"
1h"
xg"
0f"
0e"
1d"
xc"
1b"
0a"
0`"
1_"
1^"
0]"
1\"
x["
0Z"
0Y"
1X"
xW"
1V"
0U"
0T"
1S"
1R"
0Q"
1P"
xO"
0N"
0M"
1L"
xK"
1J"
0I"
0H"
1G"
1F"
0E"
1D"
xC"
0B"
0A"
1@"
x?"
1>"
0="
0<"
1;"
1:"
09"
18"
x7"
06"
05"
14"
x3"
12"
01"
00"
1/"
1."
0-"
1,"
x+"
0*"
0)"
1("
x'"
1&"
0%"
0$"
1#"
1""
0!"
1~
x}
0|
0{
1z
xy
1x
0w
0v
1u
1t
0s
1r
xq
0p
0o
1n
xm
1l
0k
0j
1i
1h
0g
1f
xe
0d
0c
1b
xa
1`
0_
0^
1]
1\
0[
1Z
xY
0X
0W
1V
xU
1T
0S
0R
1Q
1P
0O
1N
xM
0L
0K
1J
xI
1H
0G
0F
1E
1D
0C
1B
xA
0@
0?
1>
x=
0<
0;
0:
09
08
17
06
x5
14
13
12
x1
00
0/
0.
0-
0,
1+
0*
x)
1(
1'
1&
bx %
b11 $
b11 #
0"
bx !
$end
#5
1)
15
1I
1U
1a
1m
1y
1'"
13"
1?"
1K"
1W"
1c"
1o"
1{"
1)#
0+
01
07
0=
0B
0A
0N
0M
0Z
0Y
0f
0e
0r
0q
0~
0}
0,"
0+"
08"
07"
0D"
0C"
0P"
0O"
0\"
0["
0h"
0g"
0t"
0s"
0"#
b11 !
b11 %
0!#
0&
1/
02
1;
0>
1F
0J
1R
0V
1^
0b
1j
0n
1v
0z
1$"
0("
10"
04"
1<"
0@"
1H"
0L"
1T"
0X"
1`"
0d"
1l"
0p"
1x"
0|"
1&#
1"
#10
0T
19
1<
1L
04
0Q
1+
16
1B
1Z
1f
1r
1~
1,"
18"
1D"
1P"
1\"
1h"
1t"
1"#
18
0P
1O
1&
0/
12
0;
1>
0F
1J
0R
1V
0^
1b
0j
1n
0v
1z
0$"
1("
00"
14"
0<"
1@"
0H"
1L"
0T"
1X"
0`"
1d"
0l"
1p"
0x"
1|"
0&#
03
1K
0"
b1001 #
b1001 $
#13
1Q
1T
0`
0l
0(#
0L
1X
1d
1~"
1N
0Z
0]
0f
0i
0"#
0%#
1P
0O
0\
1[
0h
1g
0$#
1##
0K
1W
1c
1}"
b1000000000110001 #
b1000000000110001 $
#14
1-
10
0<
0H
1]
1`
1i
1l
1%#
1(#
0(
14
1@
0X
0d
0~"
1*
06
09
0B
0E
1Z
1f
1"#
1,
0+
08
17
0D
1C
1\
0[
1h
0g
1$#
0##
0'
13
1?
0W
0c
0}"
b110 #
b110 $
#15
11
1A
0*
b110 !
b110 %
0)
07
0C
0I
0N
0Z
0f
0r
0~
0,"
08"
0D"
0P"
0\"
0h"
0t"
0"#
0&
1.
02
1;
0>
1G
0J
1R
0V
1^
0b
1j
0n
1v
0z
1$"
0("
10"
04"
1<"
0@"
1H"
0L"
1T"
0X"
1`"
0d"
1l"
0p"
1x"
0|"
1&#
1"
#18
0,
1D
1'
0?
b11 #
b11 $
#20
00
1(
1E
1H
0-
0@
1+
17
1B
1N
1Z
1f
1r
1~
1,"
18"
1D"
1P"
1\"
1h"
1t"
1"#
1&
0.
12
0;
1>
0G
1J
0R
1V
0^
1b
0j
1n
0v
1z
0$"
1("
00"
14"
0<"
1@"
0H"
1L"
0T"
1X"
0`"
1d"
0l"
1p"
0x"
1|"
0&#
0"
#25
1)
1I
0+
01
07
0B
b11 !
b11 %
0A
0N
0Z
0f
0r
0~
0,"
08"
0D"
0P"
0\"
0h"
0t"
0"#
0&
1/
02
1;
0>
1F
0J
1R
0V
1^
0b
1j
0n
1v
0z
1$"
0("
10"
04"
1<"
0@"
1H"
0L"
1T"
0X"
1`"
0d"
1l"
0p"
1x"
0|"
1&#
1"
#26
1,
18
0P
0'
03
1K
b1000 #
b1000 $
#30
0T
1-
10
19
1<
1L
0(
04
0Q
1*
16
1B
1O
1Z
1f
1r
1~
1,"
18"
1D"
1P"
1\"
1h"
1t"
1"#
1&
0/
12
0;
1>
0F
1J
0R
1V
0^
1b
0j
1n
0v
1z
0$"
1("
00"
14"
0<"
1@"
0H"
1L"
0T"
1X"
0`"
1d"
0l"
1p"
0x"
1|"
0&#
0"
#32
00
0<
0H
0`
0l
0x
0&"
02"
0>"
0J"
0V"
0b"
0n"
0z"
0(#
1(
14
1@
1X
1d
1p
1|
1*"
16"
1B"
1N"
1Z"
1f"
1r"
1~"
0*
0-
06
09
0B
0E
0Z
0]
0f
0i
0r
0u
0~
0#"
0,"
0/"
08"
0;"
0D"
0G"
0P"
0S"
0\"
0_"
0h"
0k"
0t"
0w"
0"#
0%#
0,
1+
08
17
0D
1C
0\
1[
0h
1g
0t
1s
0""
1!"
0."
1-"
0:"
19"
0F"
1E"
0R"
1Q"
0^"
1]"
0j"
1i"
0v"
1u"
0$#
1##
1'
13
1?
1W
1c
1o
1{
1)"
15"
1A"
1M"
1Y"
1e"
1q"
1}"
b1111111111111111 #
b1111111111111111 $
#35
1A
1M
1Y
1e
1q
1}
1+"
17"
1C"
1O"
1["
1g"
1s"
b1111111111111111 !
b1111111111111111 %
1!#
0+
07
0C
0I
0O
0U
0[
0a
0g
0m
0s
0y
0!"
0'"
0-"
03"
09"
0?"
0E"
0K"
0Q"
0W"
0]"
0c"
0i"
0o"
0u"
0{"
0##
0)#
0&
1/
02
1;
0>
1G
0J
1S
0V
1_
0b
1k
0n
1w
0z
1%"
0("
11"
04"
1="
0@"
1I"
0L"
1U"
0X"
1a"
0d"
1m"
0p"
1y"
0|"
1'#
1"
#39
1,
18
1D
1P
1\
1h
1t
1""
1."
1:"
1F"
1R"
1^"
1j"
1v"
1$#
0'
03
0?
0K
0W
0c
0o
0{
0)"
05"
0A"
0M"
0Y"
0e"
0q"
0}"
b0 #
b0 $
#40
1-
10
19
1<
1E
1H
1Q
1T
1]
1`
1i
1l
1u
1x
1#"
1&"
1/"
12"
1;"
1>"
1G"
1J"
1S"
1V"
1_"
1b"
1k"
1n"
1w"
1z"
1%#
1(#
0(
04
0@
0L
0X
0d
0p
0|
0*"
06"
0B"
0N"
0Z"
0f"
0r"
0~"
1*
16
1B
1N
1Z
1f
1r
1~
1,"
18"
1D"
1P"
1\"
1h"
1t"
1"#
1&
0/
12
0;
1>
0G
1J
0S
1V
0_
1b
0k
1n
0w
1z
0%"
1("
01"
14"
0="
1@"
0I"
1L"
0U"
1X"
0a"
1d"
0m"
1p"
0y"
1|"
0'#
0"
#45
11
1=
1I
1U
1a
1m
1y
1'"
13"
1?"
1K"
1W"
1c"
1o"
1{"
1)#
0*
0)
06
05
0B
0A
0N
0M
0Z
0Y
0f
0e
0r
0q
0~
0}
0,"
0+"
08"
07"
0D"
0C"
0P"
0O"
0\"
0["
0h"
0g"
0t"
0s"
0"#
b0 !
b0 %
0!#
0&
1.
02
1:
0>
1F
0J
1R
0V
1^
0b
1j
0n
1v
0z
1$"
0("
10"
04"
1<"
0@"
1H"
0L"
1T"
0X"
1`"
0d"
1l"
0p"
1x"
0|"
1&#
1"
#46
0,
08
1'
13
b11 #
b11 $
#50
00
0<
1(
14
0-
09
1+
17
1B
1N
1Z
1f
1r
1~
1,"
18"
1D"
1P"
1\"
1h"
1t"
1"#
1&
0.
12
0:
1>
0F
1J
0R
1V
0^
1b
0j
1n
0v
1z
0$"
1("
00"
14"
0<"
1@"
0H"
1L"
0T"
1X"
0`"
1d"
0l"
1p"
0x"
1|"
0&#
0"
#55
1)
b11 !
b11 %
15
0+
01
07
0=
0B
0N
0Z
0f
0r
0~
0,"
08"
0D"
0P"
0\"
0h"
0t"
0"#
0&
1/
02
1;
0>
1F
0J
1R
0V
1^
0b
1j
0n
1v
0z
1$"
0("
10"
04"
1<"
0@"
1H"
0L"
1T"
0X"
1`"
0d"
1l"
0p"
1x"
0|"
1&#
1"
#60
1+
17
1B
1N
1Z
1f
1r
1~
1,"
18"
1D"
1P"
1\"
1h"
1t"
1"#
1&
0/
12
0;
1>
0F
1J
0R
1V
0^
1b
0j
1n
0v
1z
0$"
1("
00"
14"
0<"
1@"
0H"
1L"
0T"
1X"
0`"
1d"
0l"
1p"
0x"
1|"
0&#
0"
#65
0+
07
0B
0N
0Z
0f
0r
0~
0,"
08"
0D"
0P"
0\"
0h"
0t"
0"#
0&
1/
02
1;
0>
1F
0J
1R
0V
1^
0b
1j
0n
1v
0z
1$"
0("
10"
04"
1<"
0@"
1H"
0L"
1T"
0X"
1`"
0d"
1l"
0p"
1x"
0|"
1&#
1"
