DDaCA/Verilog/d_latch.v
module d_latch (
    input en,
    input d,
    output q
);
    wire nd;
    wire and1, and2;
    wire nor1, nor2;
    
    not d_inv(nd, d);
    and and_1(and1, nd, en);
    and and_2(and2, d, en);
    nor nor_1(nor1, and1, nor2);
    nor nor_2(nor2, and2, nor1);

    assign q = nor1;
endmodule

DDaCA/Verilog/d_flip_flop2.v
`include "d_latch.v"

module d_flip_flop2 (
    input clk,
    input d,
    output q
);
    wire nclk, tmp;

    not clk_inv(nclk, clk);
    d_latch master(nclk, d, tmp);
    d_latch slave(clk, tmp, q);
endmodule

DDaCA/Verilog/d_flip_flop2_tb.v
module d_flip_flop2_tb ();
    reg clk = 0, d;
    wire q;

    always #5 clk = !clk;

    d_flip_flop2 dut(clk, d, q);

    initial begin
        $dumpfile("d_flip_flop2.vcd");
        $dumpvars(0, d_flip_flop2_tb);

        d = 0;
        #10;
        d = 1;
        #3;
        d = 0;
        #1;
        d = 1;
        #4;
        d = 0;
        #8;
        d = 1;
        #6;
        d = 0;
        #7;
        d = 1;
        #7;
        d = 0;
        #20;
        $finish;
    end

    initial
     $monitor("At time %t, q = %h",
              $time, q);
endmodule

DDaCA/Verilog/d_flip_flop2.vcd
$date
	Sat Jun 19 15:10:39 2021
$end
$version
	Icarus Verilog
$end
$timescale
	1s
$end
$scope module d_flip_flop2_tb $end
$var wire 1 ! q $end
$var reg 1 " clk $end
$var reg 1 # d $end
$scope module dut $end
$var wire 1 " clk $end
$var wire 1 # d $end
$var wire 1 $ nclk $end
$var wire 1 % tmp $end
$var wire 1 ! q $end
$scope module master $end
$var wire 1 & and1 $end
$var wire 1 ' and2 $end
$var wire 1 # d $end
$var wire 1 $ en $end
$var wire 1 ( nd $end
$var wire 1 ) nor1 $end
$var wire 1 * nor2 $end
$var wire 1 % q $end
$upscope $end
$scope module slave $end
$var wire 1 + and1 $end
$var wire 1 , and2 $end
$var wire 1 % d $end
$var wire 1 " en $end
$var wire 1 - nd $end
$var wire 1 . nor1 $end
$var wire 1 / nor2 $end
$var wire 1 ! q $end
$upscope $end
$upscope $end
$upscope $end
$enddefinitions $end
#0
$dumpvars
x/
x.
1-
0,
0+
1*
0)
1(
0'
1&
0%
1$
0#
0"
x!
$end
#5
1/
0&
0!
0.
0$
1+
1"
#10
0-
1%
1)
0*
1'
1$
0+
0(
0"
1#
#13
1*
1-
0%
0)
1&
1(
0'
0#
#14
0-
1%
1)
0&
0*
0(
1'
1#
#15
1!
1.
0'
0/
0$
1,
1"
#18
1(
0#
#20
1*
1-
0%
0)
1&
1$
0,
0"
#25
1/
0&
0!
0.
0$
1+
1"
#26
0(
1#
#30
0-
1%
1)
0*
1'
1$
0+
0"
#32
1*
1-
0%
0)
1&
1(
0'
0#
#35
0&
0$
1+
1"
#39
0(
1#
#40
0-
1%
1)
0*
1'
1$
0+
0"
#45
1!
1.
0'
0/
0$
1,
1"
#46
1(
0#
#50
1*
1-
0%
0)
1&
1$
0,
0"
#55
1/
0&
0!
0.
0$
1+
1"
#60
1&
1$
0+
0"
#65
0&
0$
1+
1"
