DDaCA/Verilog/d_latch.v
module d_latch (
    input en,
    input d,
    output q
);
    wire nd;
    wire and1, and2;
    wire nor1, nor2;
    
    not d_inv(nd, d);
    and and_1(and1, nd, en);
    and and_2(and2, d, en);
    nor nor_1(nor1, and1, nor2);
    nor nor_2(nor2, and2, nor1);

    assign q = nor1;
endmodule

DDaCA/Verilog/d_latch_tb.v
module d_latch_tb ();
    reg en, d;
    wire q;

    // instantiate device under test
    d_latch dut(en, d, q);

    // apply inputs one at a time
    initial begin
        $dumpfile("d_latch.vcd");
        $dumpvars(0, d_latch_tb);

        en = 0; d = 0;  #10; // q = x
        d = 1;          #10; // q = x
        en = 1; d = 0;  #10; // q = 0
        d = 1;          #10; // q = 1
        en = 0; d = 0;  #10; // q = 1
        d = 1;          #10; // q = 1
        d = 0;          #10; // q = 1
        en = 1;         #10; // q = 0
        d = 1;          #10; // q = 1
        en = 0;         #10; // q = 1
        d = 0;          #10; // q = 1
        $finish;
    end

    initial
     $monitor("At time %t, value = %h (%0d)",
              $time, q, q);
endmodule

DDaCA/Verilog/d_latch.vcd
$date
	Sat Jun 19 14:55:16 2021
$end
$version
	Icarus Verilog
$end
$timescale
	1s
$end
$scope module d_latch_tb $end
$var wire 1 ! q $end
$var reg 1 " d $end
$var reg 1 # en $end
$scope module dut $end
$var wire 1 $ and1 $end
$var wire 1 % and2 $end
$var wire 1 " d $end
$var wire 1 # en $end
$var wire 1 & nd $end
$var wire 1 ' nor1 $end
$var wire 1 ( nor2 $end
$var wire 1 ! q $end
$upscope $end
$upscope $end
$enddefinitions $end
#0
$dumpvars
x(
x'
1&
0%
0$
0#
0"
x!
$end
#10
0&
1"
#20
1(
0!
0'
1$
1&
0"
1#
#30
1!
1'
0$
0(
0&
1%
1"
#40
1&
0%
0"
0#
#50
0&
1"
#60
1&
0"
#70
1(
0!
0'
1$
1#
#80
1!
1'
0$
0(
0&
1%
1"
#90
0%
0#
#100
1&
0"
