DDaCA/Turing-Machine/ram.v
module ram #(
    parameter DATA_WIDTH = 32,
    parameter ADDR_SPACE = 14
) (
    input [ADDR_SPACE-1:0] addr,
    input [DATA_WIDTH-1:0] data,
    input clk,
    input we,
    output reg [DATA_WIDTH-1:0] out
);
    reg [DATA_WIDTH-1:0] mem [2**ADDR_SPACE-1:0];

    always @(posedge clk) begin
        if (we) begin
            mem[addr] <= data;
        end
        out <= mem[addr];
    end
endmodule

DDaCA/Turing-Machine/test_bench/ram_tb.v
// `include "../ram.v"

module ram_tb ();
    parameter DATA_WIDTH = 32;
    parameter ADDR_SPACE = 14;

    reg clk = 0;
    reg [ADDR_SPACE-1:0] addr = 0;
    reg [DATA_WIDTH-1:0] d;
    wire [DATA_WIDTH-1:0] out;
    reg we = 1;

    always #5 clk = !clk;

    ram #(DATA_WIDTH, ADDR_SPACE) mem(addr, d, clk, we, out);

    initial begin
        $dumpfile("ram.vcd");
        $dumpvars(0, ram_tb);

        d = 16'b11;
        #10;
        d = 16'b1001;
        #3;
        d = 16'b1000_0000_0011_0001; we = 0;
        #1;
        d = 16'b110;
        #4;
        d = 16'b11; we = 1;
        #8;
        d = 16'b1000;
        #6;
        d = 16'hFF_FF;
        #7;
        d = 16'b0; we = 0;
        #7;
        d = 16'b11;
        #20;
        $finish;
    end

    initial
     $monitor("At time %t, q = %h",
              $time, out);
endmodule

DDaCA/Turing-Machine/test_bench/ram.vcd
$date
	Thu Jul  8 23:11:18 2021
$end
$version
	Icarus Verilog
$end
$timescale
	1s
$end
$scope module ram_tb $end
$var wire 32 ! out [31:0] $end
$var reg 14 " addr [13:0] $end
$var reg 1 # clk $end
$var reg 32 $ d [31:0] $end
$var reg 1 % we $end
$scope module mem $end
$var wire 14 & addr [13:0] $end
$var wire 1 # clk $end
$var wire 32 ' data [31:0] $end
$var wire 1 % we $end
$var reg 32 ( out [31:0] $end
$upscope $end
$upscope $end
$enddefinitions $end
#0
$dumpvars
bx (
b11 '
b0 &
1%
b11 $
0#
b0 "
bx !
$end
#5
1#
#10
0#
b1001 $
b1001 '
#13
0%
b1000000000110001 $
b1000000000110001 '
#14
b110 $
b110 '
#15
b11 !
b11 (
1#
#18
1%
b11 $
b11 '
#20
0#
#25
1#
#26
b1000 $
b1000 '
#30
0#
#32
b1111111111111111 $
b1111111111111111 '
#35
1#
#39
0%
b0 $
b0 '
#40
0#
#45
b1111111111111111 !
b1111111111111111 (
1#
#46
b11 $
b11 '
